<?xml version="1.0" encoding="utf-8" ?>
		<hibernate-mapping xmlns="urn:nhibernate-mapping-2.2"
		                   assembly="PracticaDSMGenNHibernate"
		                   namespace="PracticaDSMGenNHibernate.EN.DSMPracticas">
		    
		    
			
				<class name="ComunidadEN" table="Comunidad"> 
						<id name="Nombre" column="attribute"/> 
			
					
					<property name="Descripcion" type="string"> 
						<column name="descripcion"  not-null="true"/>
					</property>
					<property name="FechaCreacion" type="date"> 
						<column name="fechaCreacion"  not-null="true"/>
					</property>
			
			
			
			
			
		  			
						<bag name="Usuario" table="[comunidad_usuario]"  >
							<key>
								
									<column name="FK_attribute_idComunidad"/> 
							</key>
      						<many-to-many class="PracticaDSMGenNHibernate.EN.DSMPracticas.UsuarioEN">
									<column name="FK_attribute_idUsuario"/> 
      						</many-to-many>
    					</bag>
			
		  			
						<bag name="Post" cascade="delete">
							<key>
							
								
								<column name="FK_attribute_idComunidad"/>
					      	</key>
							<one-to-many class="PracticaDSMGenNHibernate.EN.DSMPracticas.PostEN"/>
					    </bag>
					
			
		  			
					
							   <one-to-one name="Juego" class="PracticaDSMGenNHibernate.EN.DSMPracticas.JuegoEN" property-ref="Comunidad" />							
					 
						
					
					
					
					
					
					
		
		 </class>	
		  
		  <query name="ComunidadENReadAllHQL">from ComunidadEN</query>
		</hibernate-mapping>
	